terrapyn/__init__.py
terrapyn/ee/__init__.py
terrapyn/ee/auth.py
terrapyn/ee/data.py
terrapyn/ee/io.py
terrapyn/ee/stats.py
terrapyn/ee/timeseries.py
terrapyn/ee/utils.py
terrapyn_ee-0.1.0.dist-info/METADATA
terrapyn_ee-0.1.0.dist-info/WHEEL
terrapyn_ee-0.1.0.dist-info/licenses/LICENSE.md
terrapyn_ee-0.1.0.dist-info/RECORD
