Metadata-Version: 2.4
Name: terrapyn-ee
Version: 0.1.0
Summary: Earth Engine module for terrapyn toolkit.
Author-email: Colin Hill <colinalastairhill@gmail.com>
License: BSD License
License-File: LICENSE.md
Classifier: Development Status :: 5 - Production/Stable
Classifier: Intended Audience :: Developers
Classifier: License :: OSI Approved :: BSD License
Classifier: Programming Language :: Python :: 3.10
Classifier: Programming Language :: Python :: 3.11
Classifier: Programming Language :: Python :: 3.12
Classifier: Programming Language :: Python :: 3.13
Requires-Python: >=3.10
Requires-Dist: earthengine-api>=1.6.4
Requires-Dist: geemap>=0.36.1
Requires-Dist: terrapyn>=0.3.0
